pyspider/__init__.py
pyspider/logging.conf
pyspider/run.py
pyspider/database/__init__.py
pyspider/database/basedb.py
pyspider/database/base/__init__.py
pyspider/database/base/projectdb.py
pyspider/database/base/resultdb.py
pyspider/database/base/taskdb.py
pyspider/database/elasticsearch/__init__.py
pyspider/database/elasticsearch/projectdb.py
pyspider/database/elasticsearch/resultdb.py
pyspider/database/elasticsearch/taskdb.py
pyspider/database/local/__init__.py
pyspider/database/local/projectdb.py
pyspider/database/mongodb/__init__.py
pyspider/database/mongodb/mongodbbase.py
pyspider/database/mongodb/projectdb.py
pyspider/database/mongodb/resultdb.py
pyspider/database/mongodb/taskdb.py
pyspider/database/mysql/__init__.py
pyspider/database/mysql/mysqlbase.py
pyspider/database/mysql/projectdb.py
pyspider/database/mysql/resultdb.py
pyspider/database/mysql/taskdb.py
pyspider/database/redis/__init__.py
pyspider/database/redis/taskdb.py
pyspider/database/sqlalchemy/__init__.py
pyspider/database/sqlalchemy/projectdb.py
pyspider/database/sqlalchemy/resultdb.py
pyspider/database/sqlalchemy/sqlalchemybase.py
pyspider/database/sqlalchemy/taskdb.py
pyspider/database/sqlite/__init__.py
pyspider/database/sqlite/projectdb.py
pyspider/database/sqlite/resultdb.py
pyspider/database/sqlite/sqlitebase.py
pyspider/database/sqlite/taskdb.py
pyspider/fetcher/__init__.py
pyspider/fetcher/cookie_utils.py
pyspider/fetcher/phantomjs_fetcher.js
pyspider/fetcher/splash_fetcher.lua
pyspider/fetcher/tornado_fetcher.py
pyspider/libs/ListIO.py
pyspider/libs/__init__.py
pyspider/libs/base_handler.py
pyspider/libs/bench.py
pyspider/libs/counter.py
pyspider/libs/dataurl.py
pyspider/libs/log.py
pyspider/libs/multiprocessing_queue.py
pyspider/libs/pprint.py
pyspider/libs/response.py
pyspider/libs/result_dump.py
pyspider/libs/sample_handler.py
pyspider/libs/url.py
pyspider/libs/utils.py
pyspider/libs/wsgi_xmlrpc.py
pyspider/message_queue/__init__.py
pyspider/message_queue/beanstalk.py
pyspider_mark-0.3.10.dist-info/LICENSE
pyspider_mark-0.3.10.dist-info/METADATA
pyspider_mark-0.3.10.dist-info/WHEEL
pyspider_mark-0.3.10.dist-info/entry_points.txt
pyspider_mark-0.3.10.dist-info/top_level.txt
pyspider_mark-0.3.10.dist-info/RECORD
