Metadata-Version: 2.1
Name: pyspider-mark
Version: 0.3.10
Summary: 兼容Python3.7的pyspider
Home-page: https://segmentfault.com/u/xiaomage_5a60560a90a98
Author: Mark
Author-email: oldmark@dingtalk.com
License: Apache License, Version 2.0
Keywords: pyspider scrapy crawler spider webui python3.7
Platform: UNKNOWN
Classifier: Development Status :: 4 - Beta
Classifier: Programming Language :: Python :: 2
Classifier: Programming Language :: Python :: 2.6
Classifier: Programming Language :: Python :: 2.7
Classifier: Programming Language :: Python :: 3
Classifier: Programming Language :: Python :: 3.3
Classifier: Programming Language :: Python :: 3.4
Classifier: Programming Language :: Python :: 3.5
Classifier: License :: OSI Approved :: Apache Software License
Classifier: Intended Audience :: Developers
Classifier: Operating System :: OS Independent
Classifier: Environment :: Web Environment
Classifier: Topic :: Internet :: WWW/HTTP
Classifier: Topic :: Software Development :: Libraries :: Application Frameworks
Classifier: Topic :: Software Development :: Libraries :: Python Modules
Requires-Dist: Flask (>=0.10)
Requires-Dist: Jinja2 (>=2.7)
Requires-Dist: chardet (>=2.2)
Requires-Dist: cssselect (>=0.9)
Requires-Dist: lxml
Requires-Dist: pycurl
Requires-Dist: requests (>=2.2)
Requires-Dist: Flask-Login (>=0.2.11)
Requires-Dist: u-msgpack-python (>=1.6)
Requires-Dist: click (>=3.3)
Requires-Dist: six (>=1.5.0)
Requires-Dist: tblib (>=1.3.0)
Requires-Dist: wsgidav (>=2.0.0)
Requires-Dist: tornado (<=4.5.3,>=3.2)
Requires-Dist: pyquery
Provides-Extra: all
Requires-Dist: mysql-connector-python (>=1.2.2) ; extra == 'all'
Requires-Dist: pymongo (>=2.7.2) ; extra == 'all'
Requires-Dist: redis ; extra == 'all'
Requires-Dist: redis-py-cluster ; extra == 'all'
Requires-Dist: psycopg2 ; extra == 'all'
Requires-Dist: elasticsearch (<2.4.0,>=2.0.0) ; extra == 'all'
Requires-Dist: kombu ; extra == 'all'
Requires-Dist: amqp (>=2.1.1) ; extra == 'all'
Requires-Dist: SQLAlchemy (>=0.9.7) ; extra == 'all'
Provides-Extra: test
Requires-Dist: unittest2 (>=0.5.1) ; extra == 'test'
Requires-Dist: coverage ; extra == 'test'
Requires-Dist: httpbin (<=0.5.0) ; extra == 'test'
Requires-Dist: pyproxy (>=0.1.6) ; extra == 'test'
Requires-Dist: easywebdav ; extra == 'test'
